mamba_django/__init__.py
mamba_django/mamba_runner.py
mamba_django-0.8.0.dist-info/LICENSE
mamba_django-0.8.0.dist-info/METADATA
mamba_django-0.8.0.dist-info/WHEEL
mamba_django-0.8.0.dist-info/top_level.txt
mamba_django-0.8.0.dist-info/RECORD
