Metadata-Version: 2.1
Name: mamba-django
Version: 0.8.0
Summary: A Django test runner for mamba (the definitive test runner for Python).
Home-page: https://github.com/quiqueporta/mamba-django
Author: Quique Porta
Author-email: quiqueporta@gmail.com
License: MIT/X11
Download-URL: https://github.com/quiqueporta/mamba-django/releases
Keywords: python,bdd,testing,tdd,django
Platform: UNKNOWN
Classifier: Development Status :: 5 - Production/Stable
Classifier: Intended Audience :: Developers
Classifier: Natural Language :: English
Classifier: Operating System :: OS Independent
Classifier: Programming Language :: Python
Classifier: Topic :: Utilities
Requires-Dist: Django (>=1.11)
Requires-Dist: mamba
